debiaiServer/__init__.py
debiaiServer/debiai_gui_utils.py
debiaiServer/init.py
debiaiServer/swagger.yaml
debiaiServer/websrv.py
debiaiServer/api/__init__.py
debiaiServer/api/v1/__init__.py
debiaiServer/api/v1/debiai/__init__.py
debiaiServer/api/v1/debiai/dataprovider.py
debiaiServer/api/v1/debiai/layouts.py
debiaiServer/api/v1/debiai/projects.py
debiaiServer/api/v1/debiai/swagger.yaml
debiaiServer/api/v1/debiai/utils.py
debiaiServer/api/v1/exploration/__init__.py
debiaiServer/api/v1/exploration/controller.py
debiaiServer/api/v1/exploration/swagger.yaml
debiaiServer/api/v1/exploration/utils.py
debiaiServer/api/v1/exploration_statistics/__init__.py
debiaiServer/api/v1/exploration_statistics/controller.py
debiaiServer/api/v1/exploration_statistics/swagger.yaml
debiaiServer/api/v1/exploration_statistics/utils.py
debiaiServer/api/v1/json_block_provider/__init__.py
debiaiServer/api/v1/json_block_provider/dataprovider.py
debiaiServer/api/v1/json_block_provider/swagger.yaml
debiaiServer/config/__init__.py
debiaiServer/config/config.ini
debiaiServer/config/init_config.py
debiaiServer/controller/__init__.py
debiaiServer/controller/algoProviders.py
debiaiServer/controller/data.py
debiaiServer/controller/dataProviders.py
debiaiServer/controller/exportMethods.py
debiaiServer/controller/layouts.py
debiaiServer/controller/models.py
debiaiServer/controller/projects.py
debiaiServer/controller/pythonModuleDp.py
debiaiServer/controller/selection.py
debiaiServer/controller/widgetConfigurations.py
debiaiServer/dist/favicon.ico
debiaiServer/dist/index.html
debiaiServer/dist/css/300.753db418.css
debiaiServer/dist/css/32.11a9f1e6.css
debiaiServer/dist/css/429.94575cee.css
debiaiServer/dist/css/584.6c501d2d.css
debiaiServer/dist/css/936.afe0dc2b.css
debiaiServer/dist/css/app.258d7f8e.css
debiaiServer/dist/img/Question.547ff839.png
debiaiServer/dist/img/addColumn.ab8459bd.svg
debiaiServer/dist/img/aggregation.7950a8db.svg
debiaiServer/dist/img/algorithm.8fab7c56.svg
debiai_gui-0.32.1.dist-info/LICENSE
debiai_gui-0.32.1.dist-info/METADATA
debiai_gui-0.32.1.dist-info/WHEEL
debiai_gui-0.32.1.dist-info/entry_points.txt
debiai_gui-0.32.1.dist-info/top_level.txt
debiai_gui-0.32.1.dist-info/RECORD
