Metadata-Version: 2.1
Name: debiai-gui
Version: 0.32.1
Summary: DebiAI easy start module, the standalone version of DebiAI
Home-page: https://github.com/debiai/DebiAI
Author: IRT-Systemx
Author-email: debiai@irt-systemx.fr
Classifier: Programming Language :: Python :: 3
Requires-Python: >=3.6
License-File: LICENSE
Requires-Dist: Flask==2.0.3
Requires-Dist: flask-cors==3.0.8
Requires-Dist: connexion==2.6.0
Requires-Dist: requests==2.25.1
Requires-Dist: swagger-ui-bundle==0.0.5
Requires-Dist: ujson==5.8.0
Requires-Dist: kafka-python==2.0.2
Requires-Dist: openapi-spec-validator==0.2.8
Requires-Dist: PyYAML==6.0
Requires-Dist: cacheout==0.14.1
Requires-Dist: termcolor==2.3.0
Requires-Dist: werkzeug==2.2.2
Requires-Dist: psutil==6.0.0
Requires-Dist: waitress==3.0.0
Requires-Dist: pickledb==1.3.2
Requires-Dist: setuptools==80.9.0
